hurtful_py/__init__.py
hurtful_py/main.py
hurtful_py/microphone_reader.py
tests/__init__.py
tests/test_mic.py
hurtful_py-0.0.2.dist-info/LICENSE
hurtful_py-0.0.2.dist-info/METADATA
hurtful_py-0.0.2.dist-info/WHEEL
hurtful_py-0.0.2.dist-info/top_level.txt
hurtful_py-0.0.2.dist-info/RECORD
