Metadata-Version: 2.1
Name: hurtful-py
Version: 0.0.2
Summary: HurtFul Python SDK
Home-page: 
Author: Danil Dyachenko (Puker228)
Author-email: karatelanalov@yandex.ru
Project-URL: GitHub, https://github.com/hurtful/hurtful-py
Classifier: Programming Language :: Python :: 3.11
Classifier: License :: OSI Approved :: MIT License
Classifier: Operating System :: OS Independent
Requires-Python: >=3.11
License-File: LICENSE
Requires-Dist: pyaudio
